rustdoc_mcp/__init__.py
rustdoc_mcp/__main__.py
rustdoc_mcp/cache.py
rustdoc_mcp/documentation.py
rustdoc_mcp/main.py
rustdoc_mcp/server.py
rustdoc_mcp/utils.py
rustdoc_mcp-0.1.5.dist-info/METADATA
rustdoc_mcp-0.1.5.dist-info/WHEEL
rustdoc_mcp-0.1.5.dist-info/entry_points.txt
rustdoc_mcp-0.1.5.dist-info/RECORD
