Metadata-Version: 2.4
Name: rustdoc-mcp
Version: 0.1.5
Summary: MCP server for Rust documentation
Author: Tobias Kragholm
License: MIT
Requires-Python: >=3.10
Requires-Dist: beautifulsoup4
Requires-Dist: mcp
Requires-Dist: pydantic
Requires-Dist: rich
